chouseisan_py/__init__.py
chouseisan_py/_pages.py
chouseisan_py/chouseisan.py
chouseisan_py/exceptions.py
chouseisan_py/py.typed
chouseisan_py-0.1.1.dist-info/LICENSE
chouseisan_py-0.1.1.dist-info/WHEEL
chouseisan_py-0.1.1.dist-info/METADATA
chouseisan_py-0.1.1.dist-info/RECORD
