Metadata-Version: 2.1
Name: chouseisan-py
Version: 0.1.1
Summary: Automate the operation of chouseisan.com
Home-page: https://github.com/ryu22e/chouseisan_py
License: MIT
Author: Ryuji TSUTSUI
Author-email: ryu22e@gmail.com
Requires-Python: >=3.7,<4.0
Classifier: License :: OSI Approved :: MIT License
Classifier: Programming Language :: Python :: 3
Classifier: Programming Language :: Python :: 3.10
Classifier: Programming Language :: Python :: 3.7
Classifier: Programming Language :: Python :: 3.8
Classifier: Programming Language :: Python :: 3.9
Requires-Dist: beautifulsoup4 (>=4.10.0,<5.0.0)
Requires-Dist: requests (>=2.27.1,<3.0.0)
Project-URL: Repository, https://github.com/ryu22e/chouseisan_py
